Metadata-Version: 2.1
Name: KashierPayment
Version: 0.0.1
Summary: A very basic Kashier api
Home-page: 
Author: Kashier Team
Author-email: mghanem@kashier.io
License: MIT
Keywords: kashier payment
Classifier: Development Status :: 5 - Production/Stable
Classifier: Intended Audience :: Education
Classifier: Operating System :: Microsoft :: Windows :: Windows 10
Classifier: License :: OSI Approved :: MIT License
Classifier: Programming Language :: Python :: 3
License-File: LICENCE.txt
